mill_bin/__init__.py
mill_bin/main.py
mill_bin/version.py
mill_bin/assets/mill
mill_bin-0.3.1.dist-info/METADATA
mill_bin-0.3.1.dist-info/WHEEL
mill_bin-0.3.1.dist-info/entry_points.txt
mill_bin-0.3.1.dist-info/top_level.txt
mill_bin-0.3.1.dist-info/RECORD
