Metadata-Version: 2.1
Name: mill-bin
Version: 0.3.1
Summary: Mill Binary is a fat JAR with all of its dependencies.
Home-page: https://github.com/jlsemi
Author: Leway Colin@JLSemi
Author-email: colinlin@jlsemi.com
License: Apache-2.0 License
Keywords: mill
Platform: UNKNOWN
Requires-Python: >=3.6
